Metadata-Version: 2.1
Name: securehash
Version: 0.0.1
Summary: Python package to use encryption, bad encryption.
Home-page: UNKNOWN
Author: barton222
Author-email: author@example.com
License: UNKNOWN
Platform: UNKNOWN
Classifier: Programming Language :: Python :: 3
Classifier: Operating System :: OS Independent
Requires-Python: >=3.6
